{
  "proc_name": "Intel Core i7-10510U @ 1.80 GHz",
  "debug_classic_ms": 656.2868,
  "release": {
    "fixed_N": 512,
    "fixed_S": 64,
    "fixed_M": 4,
    "classic_ms": 314.8986,
    "transpose_ms": 214.3593,
    "transpose_noT_ms": 179.7992,
    "buffered_ms": 105.1067,
    "block_ms": 119.7587,
    "buffered_M_values": [
      1,
      2,
      4,
      8,
      16
    ],
    "buffered_M_times_ms": [
      353.2887,
      216.0309,
      114.1872,
      85.5494,
      97.4769
    ],
    "block_S_values": [
      1,
      2,
      4,
      8,
      16,
      32,
      64,
      128,
      256
    ],
    "block_S_times_ms": [
      2359.5759,
      613.3122,
      281.6843,
      191.933,
      127.9035,
      114.2703,
      122.0511,
      128.8616,
      113.8395
    ],
    "block_M_values": [
      1,
      2,
      4,
      8,
      16
    ],
    "block_M_times_ms": [
      294.4235,
      197.7348,
      110.2899,
      77.9956,
      91.9139
    ],
    "sweep_N_values": [
      32,
      64,
      128,
      256,
      512,
      1024,
      2048
    ],
    "sweep_classic_ms": [
      0.0316,
      0.2709,
      3.0718,
      24.9736,
      295.2528,
      2178.4278,
      175758.5733
    ],
    "sweep_transpose_ms": [
      0.0291,
      0.2894,
      2.6022,
      23.3326,
      176.2088,
      1360.7234,
      12308.6075
    ],
    "sweep_buffered_ms": [
      0.0203,
      0.2379,
      1.2928,
      11.3309,
      81.1486,
      573.9705,
      5765.0055
    ],
    "sweep_block_ms": [
      0.0372,
      0.216,
      1.3169,
      10.7641,
      83.8109,
      600.1183,
      4675.782
    ]
  }
}